README.md
setup.py
u_fd/__init__.py
u_fd/fd.py
u_fd_1.egg-info/PKG-INFO
u_fd_1.egg-info/SOURCES.txt
u_fd_1.egg-info/dependency_links.txt
u_fd_1.egg-info/top_level.txt