Metadata-Version: 2.1
Name: u-fd-1
Version: 1.0.0
Summary: seal u-fd
Home-page: UNKNOWN
Author: u
Author-email: seal.xu@qq.com
License: UNKNOWN
Platform: UNKNOWN
Classifier: Programming Language :: Python :: 2
Classifier: License :: OSI Approved :: MIT License
Classifier: Operating System :: OS Independent
Requires-Python: >=2.7
